UcbCs61asSicpWithRacket/README.md
UcbCs61asSicpWithRacket/__init__.py
UcbCs61asSicpWithRacket/__main__.py
UcbCs61asSicpWithRacket/file.epub
UcbCs61asSicpWithRacket/index.html
UcbCs61asSicpWithRacket/css/__init__.py
UcbCs61asSicpWithRacket/css/annotations.css
UcbCs61asSicpWithRacket/css/main.css
UcbCs61asSicpWithRacket/css/normalize.css
UcbCs61asSicpWithRacket/css/popup.css
UcbCs61asSicpWithRacket/font/__init__.py
UcbCs61asSicpWithRacket/font/fontello.eot
UcbCs61asSicpWithRacket/font/fontello.svg
UcbCs61asSicpWithRacket/font/fontello.ttf
UcbCs61asSicpWithRacket/font/fontello.woff
UcbCs61asSicpWithRacket/img/__init__.py
UcbCs61asSicpWithRacket/img/annotator-glyph-sprite.png
UcbCs61asSicpWithRacket/img/annotator-icon-sprite.png
UcbCs61asSicpWithRacket/img/apple-touch-icon.png
UcbCs61asSicpWithRacket/img/cancelfullscreen.png
UcbCs61asSicpWithRacket/img/close.png
UcbCs61asSicpWithRacket/img/fullscreen.png
UcbCs61asSicpWithRacket/img/loader.gif
UcbCs61asSicpWithRacket/img/menu-icon.png
UcbCs61asSicpWithRacket/img/save.png
UcbCs61asSicpWithRacket/img/saved.png
UcbCs61asSicpWithRacket/img/settings-s.png
UcbCs61asSicpWithRacket/img/settings.png
UcbCs61asSicpWithRacket/img/star.png
UcbCs61asSicpWithRacket/js/__init__.py
UcbCs61asSicpWithRacket/js/epub.js
UcbCs61asSicpWithRacket/js/epub.min.js
UcbCs61asSicpWithRacket/js/epub.min.map
UcbCs61asSicpWithRacket/js/hooks.min.js
UcbCs61asSicpWithRacket/js/hooks.min.map
UcbCs61asSicpWithRacket/js/reader.js
UcbCs61asSicpWithRacket/js/reader.js.map
UcbCs61asSicpWithRacket/js/reader.min.js
UcbCs61asSicpWithRacket/js/reader.min.map
UcbCs61asSicpWithRacket/js/hooks/__init__.py
UcbCs61asSicpWithRacket/js/hooks/extensions/__init__.py
UcbCs61asSicpWithRacket/js/hooks/extensions/highlight.js
UcbCs61asSicpWithRacket/js/libs/__init__.py
UcbCs61asSicpWithRacket/js/libs/jquery.min.js
UcbCs61asSicpWithRacket/js/libs/localforage.min.js
UcbCs61asSicpWithRacket/js/libs/screenfull.js
UcbCs61asSicpWithRacket/js/libs/screenfull.min.js
ucb_cs61as_sicp_with_racket-2024.3.2.0.dist-info/METADATA
ucb_cs61as_sicp_with_racket-2024.3.2.0.dist-info/WHEEL
ucb_cs61as_sicp_with_racket-2024.3.2.0.dist-info/entry_points.txt
ucb_cs61as_sicp_with_racket-2024.3.2.0.dist-info/top_level.txt
ucb_cs61as_sicp_with_racket-2024.3.2.0.dist-info/RECORD
